rtl/output_counter.sv
module output_counter #(
    parameter int total_outputs = 9
)(
    input clk,
    input rst,
    input output_valid,

    output reg processing_done,
    output reg [31:0] output_count
);

    always @(posedge clk) begin

        if (rst) begin

            output_count <= 0;
            processing_done <= 0;

        end

        else if (!processing_done && output_valid) begin

            if (output_count == total_outputs - 1) begin

                output_count <= output_count + 1;
                processing_done <= 1;

            end

            else begin

                output_count <= output_count + 1;
            end

        end

    end

endmodule

rtl/quantizer.sv
module quantizer #(
    parameter int output_width=8,
    parameter int shift=0
)(
    input signed [31:0] data_in,
    output signed [output_width-1:0] data_out
);

wire signed [31:0] shifted_data;

assign shifted_data = data_in >>> shift;
assign data_out = shifted_data[output_width-1:0];

endmodule

rtl/relu.sv
module relu(
    input signed [31:0] data_in,
    output signed [31:0] data_out
);
assign data_out = (data_in>0) ? data_in : 32'sd0;
endmodule

rtl/mac_array.sv
module mac_array #(
    parameter int num_mac = 9
)(
    input signed [7:0] a [0:num_mac-1],
    input signed [7:0] b [0:num_mac-1],
    output reg signed [31:0] result
);
reg signed [15:0] product [0:num_mac-1];
integer i;
always @ (*) begin
   for (i=0;i<num_mac;i=i+1) begin
    product[i]=a[i]*b[i];
   end
   result=32'd0;
   for (i=0;i<num_mac;i=i+1) begin
    result=result+product[i];
   end
end
endmodule

rtl/convolution_3x3.sv
module convolution_3x3(
    input signed [7:0] pixels [0:8],
    input signed [7:0] weights [0:8],
    output signed [31:0] result
);
mac_array #(
    .num_mac(9)
) mac_engine (
    .a(pixels),
    .b(weights),
    .result(result)
);
endmodule

rtl/sliding_window_3x3.sv
module sliding_window_3x3 #(
    parameter int image_width = 5
)(
    input clk,
    input rst,
    input pixel_valid,

    input signed [7:0] pixel_in,

    output reg window_valid,
    output reg signed [7:0] window [0:8]
);

    reg signed [7:0] line_buffer1 [0:image_width-1];
    reg signed [7:0] line_buffer2 [0:image_width-1];

    reg signed [7:0] row1_left, row1_mid, row1_right;
    reg signed [7:0] row2_left, row2_mid, row2_right;
    reg signed [7:0] row3_left, row3_mid, row3_right;

    integer column;
    integer row_count;
    integer i;

    always @(posedge clk) begin

        if (rst) begin

            column <= 0;
            row_count <= 0;
            window_valid <= 0;

            row1_left <= 0;
            row1_mid <= 0;
            row1_right <= 0;

            row2_left <= 0;
            row2_mid <= 0;
            row2_right <= 0;

            row3_left <= 0;
            row3_mid <= 0;
            row3_right <= 0;

            for (i = 0; i < image_width; i = i + 1) begin
                line_buffer1[i] <= 0;
                line_buffer2[i] <= 0;
            end

            for (i = 0; i < 9; i = i + 1)
                window[i] <= 0;

        end

        else if (pixel_valid) begin

            // Shift row 1
            row1_right <= row1_mid;
            row1_mid   <= row1_left;
            row1_left  <= line_buffer2[column];

            // Shift row 2
            row2_right <= row2_mid;
            row2_mid   <= row2_left;
            row2_left  <= line_buffer1[column];

            // Shift row 3
            row3_right <= row3_mid;
            row3_mid   <= row3_left;
            row3_left  <= pixel_in;

            // Update line buffers
            line_buffer2[column] <= line_buffer1[column];
            line_buffer1[column] <= pixel_in;

            // Generate valid 3x3 window
            if ((row_count >= 2) && (column >= 2)) begin

                window[0] <= row1_mid;
                window[1] <= row1_left;
                window[2] <= line_buffer2[column];

                window[3] <= row2_mid;
                window[4] <= row2_left;
                window[5] <= line_buffer1[column];

                window[6] <= row3_mid;
                window[7] <= row3_left;
                window[8] <= pixel_in;

                window_valid <= 1;

            end
            else begin
                window_valid <= 0;
            end

            // Move column
            if (column == image_width-1) begin

                column <= 0;

                // Move to next row
                if (row_count == image_width-1)
                    row_count <= 0;
                else
                    row_count <= row_count + 1;

            end
            else begin
                column <= column + 1;
            end

        end

        else begin
            window_valid <= 0;
        end

    end

endmodule

rtl/streaming_convolution.sv
module streaming_convolution #(
    parameter int image_width = 5
)(
    input clk, rst, pixel_valid,
    input signed [7:0] pixel_in,
    input signed [7:0] weights [0:8],
    output wire output_valid,
    output wire signed [7:0] quantized_out
);
wire signed [7:0] window [0:8];
wire window_valid;
sliding_window_3x3 #(
    .image_width(image_width)
) window_generator (
    .clk(clk),
    .rst(rst),
    .pixel_valid(pixel_valid),
    .pixel_in(pixel_in),
    .window(window),
    .window_valid(window_valid)
);

wire signed [31:0] raw_conv_result;

convolution_3x3 uut(
    .weights(weights),
    .result(raw_conv_result),
    .pixels(window)
);

wire signed [31:0] relu_result;

relu dut(
    .data_in(raw_conv_result),
    .data_out(relu_result)
);

quantizer #(
    .output_width(8),
    .shift(2)
) fut(
    .data_in(relu_result),
    .data_out(quantized_out)
);

assign output_valid=window_valid;
endmodule

rtl/cnn_controller.sv
module cnn_controller(
    input clk, rst, start, processing_done,
    output reg busy, enable
);

always @ (posedge clk) begin
    if(rst) begin
        busy<=0;
        enable<=0;
    end
    else begin
        if(start && !busy) begin
            busy<=1;
            enable<=1;
        end
        else if(processing_done) begin
            busy<=0;
            enable<=0;
        end
    end
end
endmodule

rtl/cnn_accelerator.sv
module cnn_accelerator #(
    parameter int IMAGE_WIDTH = 5,
    parameter int total_outputs = 9
)(
    input clk,
    input rst,

    input start,
    input signed [7:0] pixel_in,
    input pixel_valid,

    input signed [7:0] weights [0:8],

    output wire busy,
    output wire enable,

    output wire output_valid,
    output wire signed [7:0] quantized_out,

    output wire [31:0] output_count,
    output wire processing_done
);

    wire controller_enable;

    cnn_controller controller (
        .clk(clk),
        .rst(rst),
        .start(start),
        .processing_done(processing_done),
        .busy(busy),
        .enable(controller_enable)
    );

    assign enable = controller_enable;

    wire cnn_output_valid;

    streaming_convolution #(
        .image_width(IMAGE_WIDTH)
    ) cnn_pipeline (
        .clk(clk),
        .rst(rst),
        .pixel_valid(pixel_valid && controller_enable),
        .pixel_in(pixel_in),
        .weights(weights),
        .output_valid(cnn_output_valid),
        .quantized_out(quantized_out)
    );

    assign output_valid = cnn_output_valid;

    output_counter #(
        .total_outputs(total_outputs)
    ) counter (
        .clk(clk),
        .rst(rst),
        .output_valid(cnn_output_valid),
        .processing_done(processing_done),
        .output_count(output_count)
    );
endmodule

tb/cnn_accelerator_tb.sv
`timescale 1ns/1ps

module cnn_accelerator_tb;

    localparam int IMAGE_WIDTH = 5;
    localparam int total_outputs = 9;

    reg clk;
    reg rst;
    reg start;
    reg pixel_valid;

    reg signed [7:0] pixel_in;
    reg signed [7:0] weights [0:8];

    wire busy;
    wire enable;

    wire output_valid;
    wire signed [7:0] quantized_out;

    wire [31:0] output_count;
    wire processing_done;

    cnn_accelerator #(
        .IMAGE_WIDTH(IMAGE_WIDTH),
        .total_outputs(total_outputs)
    ) uut (
        .clk(clk),
        .rst(rst),

        .start(start),
        .pixel_in(pixel_in),
        .pixel_valid(pixel_valid),

        .weights(weights),

        .busy(busy),
        .enable(enable),

        .output_valid(output_valid),
        .quantized_out(quantized_out),

        .output_count(output_count),
        .processing_done(processing_done)
    );

    always #5 clk = ~clk;

    always @(posedge clk) begin
        #1;

        if (output_valid) begin

            $display(
                "OUTPUT %0d: quantized = %0d",
                output_count,
                quantized_out
            );

        end

        if (processing_done) begin

            $display(
                "PROCESSING DONE: total outputs = %0d",
                output_count
            );

        end

    end

    initial begin

        $dumpfile("sim/cnn_accelerator.vcd");
        $dumpvars(0, cnn_accelerator_tb);

        clk = 0;
        rst = 1;
        start = 0;
        pixel_valid = 0;
        pixel_in = 0;

        weights[0] = 1;
        weights[1] = 1;
        weights[2] = 1;

        weights[3] = 1;
        weights[4] = 1;
        weights[5] = 1;

        weights[6] = 1;
        weights[7] = 1;
        weights[8] = 1;

        #12;

        @(negedge clk);

        rst = 0;

        start = 1;

        @(negedge clk);

        start = 0;
        pixel_valid = 1;

        pixel_in = 1;

        @(negedge clk); pixel_in = 2;
        @(negedge clk); pixel_in = 3;
        @(negedge clk); pixel_in = 4;
        @(negedge clk); pixel_in = 5;

        @(negedge clk); pixel_in = 6;
        @(negedge clk); pixel_in = 7;
        @(negedge clk); pixel_in = 8;
        @(negedge clk); pixel_in = 9;
        @(negedge clk); pixel_in = 10;

        @(negedge clk); pixel_in = 11;
        @(negedge clk); pixel_in = 12;
        @(negedge clk); pixel_in = 13;
        @(negedge clk); pixel_in = 14;
        @(negedge clk); pixel_in = 15;

        @(negedge clk); pixel_in = 16;
        @(negedge clk); pixel_in = 17;
        @(negedge clk); pixel_in = 18;
        @(negedge clk); pixel_in = 19;
        @(negedge clk); pixel_in = 20;

        @(negedge clk); pixel_in = 21;
        @(negedge clk); pixel_in = 22;
        @(negedge clk); pixel_in = 23;
        @(negedge clk); pixel_in = 24;
        @(negedge clk); pixel_in = 25;

        @(negedge clk);
        pixel_valid = 0;
        pixel_in = 0;

        #20;
        $finish;
    end
endmodule

sim/cnn_accelerator.vcd
$date
	Wed Sep 16 11:39:11 2026
$end
$version
	Icarus Verilog
$end
$timescale
	1ps
$end
$scope module cnn_accelerator_tb $end
$var wire 8 ! quantized_out [7:0] $end
$var wire 1 " processing_done $end
$var wire 1 # output_valid $end
$var wire 32 $ output_count [31:0] $end
$var wire 1 % enable $end
$var wire 1 & busy $end
$var reg 1 ' clk $end
$var reg 8 ( pixel_in [7:0] $end
$var reg 1 ) pixel_valid $end
$var reg 1 * rst $end
$var reg 1 + start $end
$scope module uut $end
$var wire 1 ' clk $end
$var wire 1 % enable $end
$var wire 1 # output_valid $end
$var wire 8 , pixel_in [7:0] $end
$var wire 1 ) pixel_valid $end
$var wire 1 * rst $end
$var wire 1 + start $end
$var wire 8 - quantized_out [7:0] $end
$var wire 1 " processing_done $end
$var wire 32 . output_count [31:0] $end
$var wire 1 / controller_enable $end
$var wire 1 0 cnn_output_valid $end
$var wire 1 & busy $end
$scope module cnn_pipeline $end
$var wire 1 ' clk $end
$var wire 1 0 output_valid $end
$var wire 8 1 pixel_in [7:0] $end
$var wire 1 2 pixel_valid $end
$var wire 1 * rst $end
$var wire 1 3 window_valid $end
$var wire 32 4 relu_result [31:0] $end
$var wire 32 5 raw_conv_result [31:0] $end
$var wire 8 6 quantized_out [7:0] $end
$scope module dut $end
$var wire 32 7 data_out [31:0] $end
$var wire 32 8 data_in [31:0] $end
$upscope $end
$scope module fut $end
$var wire 32 9 data_in [31:0] $end
$var wire 32 : shifted_data [31:0] $end
$var wire 8 ; data_out [7:0] $end
$upscope $end
$scope module uut $end
$var wire 32 < result [31:0] $end
$scope module mac_engine $end
$var reg 32 = result [31:0] $end
$var integer 32 > i [31:0] $end
$upscope $end
$upscope $end
$scope module window_generator $end
$var wire 1 ' clk $end
$var wire 8 ? pixel_in [7:0] $end
$var wire 1 2 pixel_valid $end
$var wire 1 * rst $end
$var reg 8 @ row1_left [7:0] $end
$var reg 8 A row1_mid [7:0] $end
$var reg 8 B row1_right [7:0] $end
$var reg 8 C row2_left [7:0] $end
$var reg 8 D row2_mid [7:0] $end
$var reg 8 E row2_right [7:0] $end
$var reg 8 F row3_left [7:0] $end
$var reg 8 G row3_mid [7:0] $end
$var reg 8 H row3_right [7:0] $end
$var reg 1 3 window_valid $end
$var integer 32 I column [31:0] $end
$var integer 32 J i [31:0] $end
$var integer 32 K row_count [31:0] $end
$upscope $end
$upscope $end
$scope module controller $end
$var wire 1 ' clk $end
$var wire 1 * rst $end
$var wire 1 + start $end
$var wire 1 " processing_done $end
$var reg 1 & busy $end
$var reg 1 / enable $end
$upscope $end
$scope module counter $end
$var wire 1 ' clk $end
$var wire 1 0 output_valid $end
$var wire 1 * rst $end
$var reg 32 L output_count [31:0] $end
$var reg 1 " processing_done $end
$upscope $end
$upscope $end
$upscope $end
$enddefinitions $end
#0
$dumpvars
bx L
bx K
bx J
bx I
bx H
bx G
bx F
bx E
bx D
bx C
bx B
bx A
bx @
b0 ?
b1001 >
bx =
bx <
bx ;
bx :
bx 9
bx 8
bx 7
bx 6
bx 5
bx 4
x3
02
b0 1
x0
x/
bx .
bx -
b0 ,
0+
1*
0)
b0 (
0'
x&
x%
bx $
x#
x"
bx !
$end
#5000
b0 !
b0 -
b0 6
b0 ;
b0 :
b0 4
b0 7
b0 9
b0 5
b0 8
b0 <
b0 =
b1001 >
0%
0/
0&
b0 H
b0 G
b0 F
b0 E
b0 D
b0 C
b0 B
b0 A
b0 @
0#
00
03
b0 K
b0 I
0"
b0 $
b0 .
b0 L
b1001 J
1'
#10000
0'
#15000
b1001 J
1'
#20000
1+
0*
0'
#25000
1%
1/
1&
1'
#30000
12
b1 (
b1 ,
b1 1
b1 ?
1)
0+
0'
#35000
b1 I
b1 F
1'
#40000
b10 (
b10 ,
b10 1
b10 ?
0'
#45000
b10 I
b10 F
b1 G
1'
#50000
b11 (
b11 ,
b11 1
b11 ?
0'
#55000
b11 I
b11 F
b10 G
b1 H
1'
#60000
b100 (
b100 ,
b100 1
b100 ?
0'
#65000
b100 I
b100 F
b11 G
b10 H
1'
#70000
b101 (
b101 ,
b101 1
b101 ?
0'
#75000
b1 K
b0 I
b101 F
b100 G
b11 H
1'
#80000
b110 (
b110 ,
b110 1
b110 ?
0'
#85000
b1 I
b110 F
b101 G
b100 H
b1 C
1'
#90000
b111 (
b111 ,
b111 1
b111 ?
0'
#95000
b10 I
b111 F
b110 G
b101 H
b10 C
b1 D
1'
#100000
b1000 (
b1000 ,
b1000 1
b1000 ?
0'
#105000
b11 I
b1000 F
b111 G
b110 H
b11 C
b10 D
b1 E
1'
#110000
b1001 (
b1001 ,
b1001 1
b1001 ?
0'
#115000
b100 I
b1001 F
b1000 G
b111 H
b100 C
b11 D
b10 E
1'
#120000
b1010 (
b1010 ,
b1010 1
b1010 ?
0'
#125000
b10 K
b0 I
b1010 F
b1001 G
b1000 H
b101 C
b100 D
b11 E
1'
#130000
b1011 (
b1011 ,
b1011 1
b1011 ?
0'
#135000
b1 I
b1011 F
b1010 G
b1001 H
b110 C
b101 D
b100 E
b1 @
1'
#140000
b1100 (
b1100 ,
b1100 1
b1100 ?
0'
#145000
b10 I
b1100 F
b1011 G
b1010 H
b111 C
b110 D
b101 E
b10 @
b1 A
1'
#150000
b1101 (
b1101 ,
b1101 1
b1101 ?
0'
#155000
b1111 !
b1111 -
b1111 6
b1111 ;
b1111 :
b111111 4
b111111 7
b111111 9
b111111 5
b111111 8
b111111 <
b111111 =
b1001 >
b11 I
1#
10
13
b1101 F
b1100 G
b1011 H
b1000 C
b111 D
b110 E
b11 @
b10 A
b1 B
1'
#160000
b1110 (
b1110 ,
b1110 1
b1110 ?
0'
#165000
b10010 !
b10010 -
b10010 6
b10010 ;
b10010 :
b1001000 4
b1001000 7
b1001000 9
b1001000 5
b1001000 8
b1001000 <
b1001000 =
b1001 >
b100 I
b1110 F
b1101 G
b1100 H
b1001 C
b1000 D
b111 E
b100 @
b11 A
b10 B
b1 $
b1 .
b1 L
1'
#170000
b1111 (
b1111 ,
b1111 1
b1111 ?
0'
#175000
b10100 !
b10100 -
b10100 6
b10100 ;
b10100 :
b1010001 4
b1010001 7
b1010001 9
b1010001 5
b1010001 8
b1010001 <
b1010001 =
b1001 >
b10 $
b10 .
b10 L
b11 K
b0 I
b1111 F
b1110 G
b1101 H
b1010 C
b1001 D
b1000 E
b101 @
b100 A
b11 B
1'
#180000
b10000 (
b10000 ,
b10000 1
b10000 ?
0'
#185000
b1 I
0#
00
03
b10000 F
b1111 G
b1110 H
b1011 C
b1010 D
b1001 E
b110 @
b101 A
b100 B
b11 $
b11 .
b11 L
1'
#190000
b10001 (
b10001 ,
b10001 1
b10001 ?
0'
#195000
b10 I
b10001 F
b10000 G
b1111 H
b1100 C
b1011 D
b1010 E
b111 @
b110 A
b101 B
1'
#200000
b10010 (
b10010 ,
b10010 1
b10010 ?
0'
#205000
b11011 !
b11011 -
b11011 6
b11011 ;
b11011 :
b1101100 4
b1101100 7
b1101100 9
b1101100 5
b1101100 8
b1101100 <
b1101100 =
b1001 >
b11 I
1#
10
13
b10010 F
b10001 G
b10000 H
b1101 C
b1100 D
b1011 E
b1000 @
b111 A
b110 B
1'
#210000
b10011 (
b10011 ,
b10011 1
b10011 ?
0'
#215000
b11101 !
b11101 -
b11101 6
b11101 ;
b11101 :
b1110101 4
b1110101 7
b1110101 9
b1110101 5
b1110101 8
b1110101 <
b1110101 =
b1001 >
b100 $
b100 .
b100 L
b100 I
b10011 F
b10010 G
b10001 H
b1110 C
b1101 D
b1100 E
b1001 @
b1000 A
b111 B
1'
#220000
b10100 (
b10100 ,
b10100 1
b10100 ?
0'
#225000
b11111 !
b11111 -
b11111 6
b11111 ;
b11111 :
b1111110 4
b1111110 7
b1111110 9
b1111110 5
b1111110 8
b1111110 <
b1111110 =
b1001 >
b100 K
b0 I
b10100 F
b10011 G
b10010 H
b1111 C
b1110 D
b1101 E
b1010 @
b1001 A
b1000 B
b101 $
b101 .
b101 L
1'
#230000
b10101 (
b10101 ,
b10101 1
b10101 ?
0'
#235000
b110 $
b110 .
b110 L
b1 I
0#
00
03
b10101 F
b10100 G
b10011 H
b10000 C
b1111 D
b1110 E
b1011 @
b1010 A
b1001 B
1'
#240000
b10110 (
b10110 ,
b10110 1
b10110 ?
0'
#245000
b10 I
b10110 F
b10101 G
b10100 H
b10001 C
b10000 D
b1111 E
b1100 @
b1011 A
b1010 B
1'
#250000
b10111 (
b10111 ,
b10111 1
b10111 ?
0'
#255000
b100110 !
b100110 -
b100110 6
b100110 ;
b100110 :
b10011001 4
b10011001 7
b10011001 9
b10011001 5
b10011001 8
b10011001 <
b10011001 =
b1001 >
b11 I
1#
10
13
b10111 F
b10110 G
b10101 H
b10010 C
b10001 D
b10000 E
b1101 @
b1100 A
b1011 B
1'
#260000
b11000 (
b11000 ,
b11000 1
b11000 ?
0'
#265000
b101000 !
b101000 -
b101000 6
b101000 ;
b101000 :
b10100010 4
b10100010 7
b10100010 9
b10100010 5
b10100010 8
b10100010 <
b10100010 =
b1001 >
b100 I
b11000 F
b10111 G
b10110 H
b10011 C
b10010 D
b10001 E
b1110 @
b1101 A
b1100 B
b111 $
b111 .
b111 L
1'
#270000
b11001 (
b11001 ,
b11001 1
b11001 ?
0'
#275000
b101010 !
b101010 -
b101010 6
b101010 ;
b101010 :
b10101011 4
b10101011 7
b10101011 9
b10101011 5
b10101011 8
b10101011 <
b10101011 =
b1001 >
b1000 $
b1000 .
b1000 L
b0 K
b0 I
b11001 F
b11000 G
b10111 H
b10100 C
b10011 D
b10010 E
b1111 @
b1110 A
b1101 B
1'
#280000
02
b0 (
b0 ,
b0 1
b0 ?
0)
0'
#285000
0#
00
03
1"
b1001 $
b1001 .
b1001 L
1'
#290000
0'
#295000
0"
0%
0/
0&
1'
