rtl/output_counter.sv
module output_counter #(
    parameter int total_outputs = 9
)(
    input clk,
    input rst,
    input output_valid,

    output reg processing_done,
    output reg [31:0] output_count
);

    always @(posedge clk) begin

        if (rst) begin

            output_count <= 0;
            processing_done <= 0;

        end

        else if (!processing_done && output_valid) begin

            if (output_count == total_outputs - 1) begin

                output_count <= output_count + 1;
                processing_done <= 1;

            end

            else begin

                output_count <= output_count + 1;
            end

        end

    end

endmodule

rtl/quantizer.sv
module quantizer #(
    parameter int output_width=8,
    parameter int shift=0
)(
    input signed [31:0] data_in,
    output signed [output_width-1:0] data_out
);

wire signed [31:0] shifted_data;

assign shifted_data = data_in >>> shift;
assign data_out = shifted_data[output_width-1:0];

endmodule

rtl/relu.sv
module relu(
    input signed [31:0] data_in,
    output signed [31:0] data_out
);
assign data_out = (data_in>0) ? data_in : 32'sd0;
endmodule

rtl/mac_array.sv
module mac_array #(
    parameter int num_mac = 9
)(
    input signed [7:0] a [0:num_mac-1],
    input signed [7:0] b [0:num_mac-1],
    output reg signed [31:0] result
);
reg signed [15:0] product [0:num_mac-1];
integer i;
always @ (*) begin
   for (i=0;i<num_mac;i=i+1) begin
    product[i]=a[i]*b[i];
   end
   result=32'd0;
   for (i=0;i<num_mac;i=i+1) begin
    result=result+product[i];
   end
end
endmodule

rtl/convolution_3x3.sv
module convolution_3x3(
    input signed [7:0] pixels [0:8],
    input signed [7:0] weights [0:8],
    output signed [31:0] result
);
mac_array #(
    .num_mac(9)
) mac_engine (
    .a(pixels),
    .b(weights),
    .result(result)
);
endmodule

rtl/sliding_window_3x3.sv
module sliding_window_3x3 #(
    parameter int image_width = 5
)(
    input clk,
    input rst,
    input pixel_valid,

    input signed [7:0] pixel_in,

    output reg window_valid,
    output reg signed [7:0] window [0:8]
);

    reg signed [7:0] line_buffer1 [0:image_width-1];
    reg signed [7:0] line_buffer2 [0:image_width-1];

    reg signed [7:0] row1_left, row1_mid, row1_right;
    reg signed [7:0] row2_left, row2_mid, row2_right;
    reg signed [7:0] row3_left, row3_mid, row3_right;

    integer column;
    integer row_count;
    integer i;

    always @(posedge clk) begin

        if (rst) begin

            column <= 0;
            row_count <= 0;
            window_valid <= 0;

            row1_left <= 0;
            row1_mid <= 0;
            row1_right <= 0;

            row2_left <= 0;
            row2_mid <= 0;
            row2_right <= 0;

            row3_left <= 0;
            row3_mid <= 0;
            row3_right <= 0;

            for (i = 0; i < image_width; i = i + 1) begin
                line_buffer1[i] <= 0;
                line_buffer2[i] <= 0;
            end

            for (i = 0; i < 9; i = i + 1)
                window[i] <= 0;

        end

        else if (pixel_valid) begin

            // Shift row 1
            row1_right <= row1_mid;
            row1_mid   <= row1_left;
            row1_left  <= line_buffer2[column];

            // Shift row 2
            row2_right <= row2_mid;
            row2_mid   <= row2_left;
            row2_left  <= line_buffer1[column];

            // Shift row 3
            row3_right <= row3_mid;
            row3_mid   <= row3_left;
            row3_left  <= pixel_in;

            // Update line buffers
            line_buffer2[column] <= line_buffer1[column];
            line_buffer1[column] <= pixel_in;

            // Generate valid 3x3 window
            if ((row_count >= 2) && (column >= 2)) begin

                window[0] <= row1_mid;
                window[1] <= row1_left;
                window[2] <= line_buffer2[column];

                window[3] <= row2_mid;
                window[4] <= row2_left;
                window[5] <= line_buffer1[column];

                window[6] <= row3_mid;
                window[7] <= row3_left;
                window[8] <= pixel_in;

                window_valid <= 1;

            end
            else begin
                window_valid <= 0;
            end

            // Move column
            if (column == image_width-1) begin

                column <= 0;

                // Move to next row
                if (row_count == image_width-1)
                    row_count <= 0;
                else
                    row_count <= row_count + 1;

            end
            else begin
                column <= column + 1;
            end

        end

        else begin
            window_valid <= 0;
        end

    end

endmodule

rtl/streaming_convolution.sv
module streaming_convolution #(
    parameter int image_width = 5
)(
    input clk, rst, pixel_valid,
    input signed [7:0] pixel_in,
    input signed [7:0] weights [0:8],
    output wire output_valid,
    output wire signed [7:0] quantized_out
);
wire signed [7:0] window [0:8];
wire window_valid;
sliding_window_3x3 #(
    .image_width(image_width)
) window_generator (
    .clk(clk),
    .rst(rst),
    .pixel_valid(pixel_valid),
    .pixel_in(pixel_in),
    .window(window),
    .window_valid(window_valid)
);

wire signed [31:0] raw_conv_result;

convolution_3x3 uut(
    .weights(weights),
    .result(raw_conv_result),
    .pixels(window)
);

wire signed [31:0] relu_result;

relu dut(
    .data_in(raw_conv_result),
    .data_out(relu_result)
);

quantizer #(
    .output_width(8),
    .shift(2)
) fut(
    .data_in(relu_result),
    .data_out(quantized_out)
);

assign output_valid=window_valid;
endmodule

rtl/cnn_controller.sv
module cnn_controller(
    input clk, rst, start, processing_done,
    output reg busy, enable
);

always @ (posedge clk) begin
    if(rst) begin
        busy<=0;
        enable<=0;
    end
    else begin
        if(start && !busy) begin
            busy<=1;
            enable<=1;
        end
        else if(processing_done) begin
            busy<=0;
            enable<=0;
        end
    end
end
endmodule

rtl/cnn_accelerator.sv
module cnn_accelerator #(
    parameter int IMAGE_WIDTH = 5,
    parameter int total_outputs = 9
)(
    input clk,
    input rst,

    input start,
    input signed [7:0] pixel_in,
    input pixel_valid,

    input signed [7:0] weights [0:8],

    output wire busy,
    output wire enable,

    output wire output_valid,
    output wire signed [7:0] quantized_out,

    output wire [31:0] output_count,
    output wire processing_done
);

    wire controller_enable;

    cnn_controller controller (
        .clk(clk),
        .rst(rst),
        .start(start),
        .processing_done(processing_done),
        .busy(busy),
        .enable(controller_enable)
    );

    assign enable = controller_enable;

    wire cnn_output_valid;

    streaming_convolution #(
        .image_width(IMAGE_WIDTH)
    ) cnn_pipeline (
        .clk(clk),
        .rst(rst),
        .pixel_valid(pixel_valid && controller_enable),
        .pixel_in(pixel_in),
        .weights(weights),
        .output_valid(cnn_output_valid),
        .quantized_out(quantized_out)
    );

    assign output_valid = cnn_output_valid;

    output_counter #(
        .total_outputs(total_outputs)
    ) counter (
        .clk(clk),
        .rst(rst),
        .output_valid(cnn_output_valid),
        .processing_done(processing_done),
        .output_count(output_count)
    );
endmodule

rtl/de10_lite_top.sv
module de10_lite_top (
    input wire CLOCK_50,

    input wire [1:0] KEY,

    output wire [9:0] LEDR
);

    // =================================================
    // Clock
    // =================================================

    wire clk;
    assign clk = CLOCK_50;


    // =================================================
    // Reset and Start
    // =================================================

    wire rst;
    wire start;

    assign rst   = ~KEY[0];
    assign start = ~KEY[1];


    // =================================================
    // Test Image
    // =================================================

    reg signed [7:0] image [0:24];

    initial begin

        image[0]  = 1;
        image[1]  = 2;
        image[2]  = 3;
        image[3]  = 4;
        image[4]  = 5;

        image[5]  = 6;
        image[6]  = 7;
        image[7]  = 8;
        image[8]  = 9;
        image[9]  = 10;

        image[10] = 11;
        image[11] = 12;
        image[12] = 13;
        image[13] = 14;
        image[14] = 15;

        image[15] = 16;
        image[16] = 17;
        image[17] = 18;
        image[18] = 19;
        image[19] = 20;

        image[20] = 21;
        image[21] = 22;
        image[22] = 23;
        image[23] = 24;
        image[24] = 25;

    end


    // =================================================
    // CNN Accelerator Signals
    // =================================================

    wire busy;
    wire enable;

    wire output_valid;
    wire signed [7:0] quantized_out;

    wire [31:0] output_count;
    wire processing_done;


    // =================================================
    // Pixel Counter
    // =================================================

    reg [5:0] pixel_index;

    always @(posedge clk) begin

        if (rst) begin
            pixel_index <= 0;
        end

        else if (!busy) begin
            pixel_index <= 0;
        end

        else if (pixel_index < 25) begin
            pixel_index <= pixel_index + 1;
        end

    end


    // =================================================
    // Pixel Generator
    // =================================================

    wire pixel_valid;
    wire signed [7:0] pixel_in;

    assign pixel_valid = busy && (pixel_index < 25);

    assign pixel_in = image[pixel_index];


    // =================================================
    // Convolution Weights
    // =================================================

    wire signed [7:0] weights [0:8];

    assign weights[0] = 1;
    assign weights[1] = 1;
    assign weights[2] = 1;

    assign weights[3] = 1;
    assign weights[4] = 1;
    assign weights[5] = 1;

    assign weights[6] = 1;
    assign weights[7] = 1;
    assign weights[8] = 1;


    // =================================================
    // CNN Accelerator
    // =================================================

    cnn_accelerator #(
        .IMAGE_WIDTH(5),
        .TOTAL_OUTPUTS(9)
    ) accelerator (

        .clk(clk),
        .rst(rst),

        .start(start),
        .pixel_in(pixel_in),
        .pixel_valid(pixel_valid),

        .weights(weights),

        .busy(busy),
        .enable(enable),

        .output_valid(output_valid),
        .quantized_out(quantized_out),

        .output_count(output_count),
        .processing_done(processing_done)

    );


    // =================================================
    // LEDs
    // =================================================

    assign LEDR[0] = busy;
    assign LEDR[1] = output_valid;
    assign LEDR[2] = processing_done;

    assign LEDR[9:3] = quantized_out[6:0];

endmodule

tb/de10_lite_top_tb.sv
`timescale 1ns/1ps

module de10_lite_top_tb;

    reg CLOCK_50;
    reg [1:0] KEY;

    wire [9:0] LEDR;

    de10_lite_top uut (
        .CLOCK_50(CLOCK_50),
        .KEY(KEY),
        .LEDR(LEDR)
    );

    // 50 MHz equivalent clock
    always #10 CLOCK_50 = ~CLOCK_50;

    initial begin

        $dumpfile("sim/de10_lite_top.vcd");
        $dumpvars(0, de10_lite_top_tb);

        CLOCK_50 = 0;

        // Both buttons released
        KEY = 2'b11;

        // Reset
        KEY[0] = 0;

        #50;

        // Release reset
        KEY[0] = 1;

        // Press START
        KEY[1] = 0;

        #20;

        // Release START
        KEY[1] = 1;

        // Allow accelerator to process
        #1000;

        $display("--------------------------------");
        $display("FINAL OUTPUT COUNT = %0d",
                 uut.output_count);
        $display("PROCESSING DONE = %0d",
                 uut.processing_done);
        $display("--------------------------------");

        $finish;

    end

endmodule

sim/de10_lite_top.vcd
$date
	Wed Sep 16 12:07:24 2026
$end
$version
	Icarus Verilog
$end
$timescale
	1ps
$end
$scope module de10_lite_top_tb $end
$var wire 10 ! LEDR [9:0] $end
$var reg 1 " CLOCK_50 $end
$var reg 2 # KEY [1:0] $end
$scope module uut $end
$var wire 1 " CLOCK_50 $end
$var wire 2 $ KEY [1:0] $end
$var wire 1 % clk $end
$var wire 8 & pixel_in [7:0] $end
$var wire 1 ' pixel_valid $end
$var wire 1 ( rst $end
$var wire 1 ) start $end
$var wire 8 * quantized_out [7:0] $end
$var wire 1 + processing_done $end
$var wire 1 , output_valid $end
$var wire 32 - output_count [31:0] $end
$var wire 1 . enable $end
$var wire 1 / busy $end
$var wire 10 0 LEDR [9:0] $end
$var reg 6 1 pixel_index [5:0] $end
$scope module accelerator $end
$var wire 1 % clk $end
$var wire 1 . enable $end
$var wire 1 , output_valid $end
$var wire 8 2 pixel_in [7:0] $end
$var wire 1 ' pixel_valid $end
$var wire 1 ( rst $end
$var wire 1 ) start $end
$var wire 8 3 quantized_out [7:0] $end
$var wire 1 + processing_done $end
$var wire 32 4 output_count [31:0] $end
$var wire 1 5 controller_enable $end
$var wire 1 6 cnn_output_valid $end
$var wire 1 / busy $end
$scope module cnn_pipeline $end
$var wire 1 % clk $end
$var wire 1 6 output_valid $end
$var wire 8 7 pixel_in [7:0] $end
$var wire 1 8 pixel_valid $end
$var wire 1 ( rst $end
$var wire 1 9 window_valid $end
$var wire 32 : relu_result [31:0] $end
$var wire 32 ; raw_conv_result [31:0] $end
$var wire 8 < quantized_out [7:0] $end
$scope module dut $end
$var wire 32 = data_out [31:0] $end
$var wire 32 > data_in [31:0] $end
$upscope $end
$scope module fut $end
$var wire 32 ? data_in [31:0] $end
$var wire 32 @ shifted_data [31:0] $end
$var wire 8 A data_out [7:0] $end
$upscope $end
$scope module uut $end
$var wire 32 B result [31:0] $end
$scope module mac_engine $end
$var reg 32 C result [31:0] $end
$var integer 32 D i [31:0] $end
$upscope $end
$upscope $end
$scope module window_generator $end
$var wire 1 % clk $end
$var wire 8 E pixel_in [7:0] $end
$var wire 1 8 pixel_valid $end
$var wire 1 ( rst $end
$var reg 8 F row1_left [7:0] $end
$var reg 8 G row1_mid [7:0] $end
$var reg 8 H row1_right [7:0] $end
$var reg 8 I row2_left [7:0] $end
$var reg 8 J row2_mid [7:0] $end
$var reg 8 K row2_right [7:0] $end
$var reg 8 L row3_left [7:0] $end
$var reg 8 M row3_mid [7:0] $end
$var reg 8 N row3_right [7:0] $end
$var reg 1 9 window_valid $end
$var integer 32 O column [31:0] $end
$var integer 32 P i [31:0] $end
$var integer 32 Q row_count [31:0] $end
$upscope $end
$upscope $end
$scope module controller $end
$var wire 1 % clk $end
$var wire 1 ( rst $end
$var wire 1 ) start $end
$var wire 1 + processing_done $end
$var reg 1 / busy $end
$var reg 1 5 enable $end
$upscope $end
$scope module counter $end
$var wire 1 % clk $end
$var wire 1 6 output_valid $end
$var wire 1 ( rst $end
$var reg 32 R output_count [31:0] $end
$var reg 1 + processing_done $end
$upscope $end
$upscope $end
$upscope $end
$upscope $end
$enddefinitions $end
#0
$dumpvars
bx R
bx Q
bx P
bx O
bx N
bx M
bx L
bx K
bx J
bx I
bx H
bx G
bx F
bx E
b1001 D
bx C
bx B
bx A
bx @
bx ?
bx >
bx =
bx <
bx ;
bx :
x9
x8
bx 7
x6
x5
bx 4
bx 3
bx 2
bx 1
bx 0
x/
x.
bx -
x,
x+
bx *
0)
1(
x'
bx &
0%
b10 $
b10 #
0"
bx !
$end
#10000
b0 *
b0 3
b0 <
b0 A
b0 @
b0 :
b0 =
b0 ?
08
b0 ;
b0 >
b0 B
b0 C
b1001 D
0'
0.
05
0/
b0 N
b0 M
b0 L
b0 K
b0 J
b0 I
b0 H
b0 G
b0 F
0,
06
09
b0 Q
b0 O
b0 !
b0 0
0+
b0 -
b0 4
b0 R
b1 &
b1 2
b1 7
b1 E
b0 1
b1001 P
1%
1"
#20000
0%
0"
#30000
b1001 P
1%
1"
#40000
0%
0"
#50000
1)
0(
b1001 P
1%
1"
b1 #
b1 $
#60000
0%
0"
#70000
18
1'
1.
15
b1 !
b1 0
1/
0)
1%
1"
b11 #
b11 $
#80000
0%
0"
#90000
b1 O
b1 L
b10 &
b10 2
b10 7
b10 E
b1 1
1%
1"
#100000
0%
0"
#110000
b11 &
b11 2
b11 7
b11 E
b10 1
b10 O
b10 L
b1 M
1%
1"
#120000
0%
0"
#130000
b11 O
b11 L
b10 M
b1 N
b100 &
b100 2
b100 7
b100 E
b11 1
1%
1"
#140000
0%
0"
#150000
b101 &
b101 2
b101 7
b101 E
b100 1
b100 O
b100 L
b11 M
b10 N
1%
1"
#160000
0%
0"
#170000
b1 Q
b0 O
b101 L
b100 M
b11 N
b110 &
b110 2
b110 7
b110 E
b101 1
1%
1"
#180000
0%
0"
#190000
b111 &
b111 2
b111 7
b111 E
b110 1
b1 O
b110 L
b101 M
b100 N
b1 I
1%
1"
#200000
0%
0"
#210000
b10 O
b111 L
b110 M
b101 N
b10 I
b1 J
b1000 &
b1000 2
b1000 7
b1000 E
b111 1
1%
1"
#220000
0%
0"
#230000
b1001 &
b1001 2
b1001 7
b1001 E
b1000 1
b11 O
b1000 L
b111 M
b110 N
b11 I
b10 J
b1 K
1%
1"
#240000
0%
0"
#250000
b100 O
b1001 L
b1000 M
b111 N
b100 I
b11 J
b10 K
b1010 &
b1010 2
b1010 7
b1010 E
b1001 1
1%
1"
#260000
0%
0"
#270000
b1011 &
b1011 2
b1011 7
b1011 E
b1010 1
b10 Q
b0 O
b1010 L
b1001 M
b1000 N
b101 I
b100 J
b11 K
1%
1"
#280000
0%
0"
#290000
b1 O
b1011 L
b1010 M
b1001 N
b110 I
b101 J
b100 K
b1 F
b1100 &
b1100 2
b1100 7
b1100 E
b1011 1
1%
1"
#300000
0%
0"
#310000
b1101 &
b1101 2
b1101 7
b1101 E
b1100 1
b10 O
b1100 L
b1011 M
b1010 N
b111 I
b110 J
b101 K
b10 F
b1 G
1%
1"
#320000
0%
0"
#330000
b1111 *
b1111 3
b1111 <
b1111 A
b1111 @
b111111 :
b111111 =
b111111 ?
b111111 ;
b111111 >
b111111 B
b111111 C
b1001 D
b11 O
b1111011 !
b1111011 0
1,
16
19
b1101 L
b1100 M
b1011 N
b1000 I
b111 J
b110 K
b11 F
b10 G
b1 H
b1110 &
b1110 2
b1110 7
b1110 E
b1101 1
1%
1"
#340000
0%
0"
#350000
b10010011 !
b10010011 0
b10010 *
b10010 3
b10010 <
b10010 A
b10010 @
b1001000 :
b1001000 =
b1001000 ?
b1001000 ;
b1001000 >
b1001000 B
b1001000 C
b1001 D
b1111 &
b1111 2
b1111 7
b1111 E
b1110 1
b1 -
b1 4
b1 R
b100 O
b1110 L
b1101 M
b1100 N
b1001 I
b1000 J
b111 K
b100 F
b11 G
b10 H
1%
1"
#360000
0%
0"
#370000
b10100011 !
b10100011 0
b10100 *
b10100 3
b10100 <
b10100 A
b10100 @
b1010001 :
b1010001 =
b1010001 ?
b1010001 ;
b1010001 >
b1010001 B
b1010001 C
b1001 D
b11 Q
b0 O
b1111 L
b1110 M
b1101 N
b1010 I
b1001 J
b1000 K
b101 F
b100 G
b11 H
b10 -
b10 4
b10 R
b10000 &
b10000 2
b10000 7
b10000 E
b1111 1
1%
1"
#380000
0%
0"
#390000
b10001 &
b10001 2
b10001 7
b10001 E
b10000 1
b11 -
b11 4
b11 R
b1 O
b10100001 !
b10100001 0
0,
06
09
b10000 L
b1111 M
b1110 N
b1011 I
b1010 J
b1001 K
b110 F
b101 G
b100 H
1%
1"
#400000
0%
0"
#410000
b10 O
b10001 L
b10000 M
b1111 N
b1100 I
b1011 J
b1010 K
b111 F
b110 G
b101 H
b10010 &
b10010 2
b10010 7
b10010 E
b10001 1
1%
1"
#420000
0%
0"
#430000
b11011 *
b11011 3
b11011 <
b11011 A
b11011 @
b1101100 :
b1101100 =
b1101100 ?
b1101100 ;
b1101100 >
b1101100 B
b1101100 C
b1001 D
b10011 &
b10011 2
b10011 7
b10011 E
b10010 1
b11 O
b11011011 !
b11011011 0
1,
16
19
b10010 L
b10001 M
b10000 N
b1101 I
b1100 J
b1011 K
b1000 F
b111 G
b110 H
1%
1"
#440000
0%
0"
#450000
b11101011 !
b11101011 0
b11101 *
b11101 3
b11101 <
b11101 A
b11101 @
b1110101 :
b1110101 =
b1110101 ?
b1110101 ;
b1110101 >
b1110101 B
b1110101 C
b1001 D
b100 O
b10011 L
b10010 M
b10001 N
b1110 I
b1101 J
b1100 K
b1001 F
b1000 G
b111 H
b100 -
b100 4
b100 R
b10100 &
b10100 2
b10100 7
b10100 E
b10011 1
1%
1"
#460000
0%
0"
#470000
b11111011 !
b11111011 0
b11111 *
b11111 3
b11111 <
b11111 A
b11111 @
b1111110 :
b1111110 =
b1111110 ?
b1111110 ;
b1111110 >
b1111110 B
b1111110 C
b1001 D
b10101 &
b10101 2
b10101 7
b10101 E
b10100 1
b101 -
b101 4
b101 R
b100 Q
b0 O
b10100 L
b10011 M
b10010 N
b1111 I
b1110 J
b1101 K
b1010 F
b1001 G
b1000 H
1%
1"
#480000
0%
0"
#490000
b1 O
b11111001 !
b11111001 0
0,
06
09
b10101 L
b10100 M
b10011 N
b10000 I
b1111 J
b1110 K
b1011 F
b1010 G
b1001 H
b110 -
b110 4
b110 R
b10110 &
b10110 2
b10110 7
b10110 E
b10101 1
1%
1"
#500000
0%
0"
#510000
b10111 &
b10111 2
b10111 7
b10111 E
b10110 1
b10 O
b10110 L
b10101 M
b10100 N
b10001 I
b10000 J
b1111 K
b1100 F
b1011 G
b1010 H
1%
1"
#520000
0%
0"
#530000
b100110 *
b100110 3
b100110 <
b100110 A
b100110 @
b10011001 :
b10011001 =
b10011001 ?
b10011001 ;
b10011001 >
b10011001 B
b10011001 C
b1001 D
b11 O
b100110011 !
b100110011 0
1,
16
19
b10111 L
b10110 M
b10101 N
b10010 I
b10001 J
b10000 K
b1101 F
b1100 G
b1011 H
b11000 &
b11000 2
b11000 7
b11000 E
b10111 1
1%
1"
#540000
0%
0"
#550000
b101000011 !
b101000011 0
b101000 *
b101000 3
b101000 <
b101000 A
b101000 @
b10100010 :
b10100010 =
b10100010 ?
b10100010 ;
b10100010 >
b10100010 B
b10100010 C
b1001 D
b11001 &
b11001 2
b11001 7
b11001 E
b11000 1
b111 -
b111 4
b111 R
b100 O
b11000 L
b10111 M
b10110 N
b10011 I
b10010 J
b10001 K
b1110 F
b1101 G
b1100 H
1%
1"
#560000
0%
0"
#570000
b101010011 !
b101010011 0
b101010 *
b101010 3
b101010 <
b101010 A
b101010 @
b10101011 :
b10101011 =
b10101011 ?
08
b10101011 ;
b10101011 >
b10101011 B
b10101011 C
b1001 D
0'
b0 Q
b0 O
b11001 L
b11000 M
b10111 N
b10100 I
b10011 J
b10010 K
b1111 F
b1110 G
b1101 H
b1000 -
b1000 4
b1000 R
bx &
bx 2
bx 7
bx E
b11001 1
1%
1"
#580000
0%
0"
#590000
1+
b1001 -
b1001 4
b1001 R
b101010101 !
b101010101 0
0,
06
09
1%
1"
#600000
0%
0"
#610000
0.
05
b101010100 !
b101010100 0
0/
1%
1"
#620000
0%
0"
#630000
b1 &
b1 2
b1 7
b1 E
b0 1
1%
1"
