rtl/mac_unit.sv
module mac_unit(
    input clk,
    input rst,
    input signed [7:0] a,
    input signed [7:0] b,
    input signed [31:0] accumulator,
    output reg signed [31:0] result
);
wire signed [15:0] product;
assign product = a * b;
always @(posedge clk) begin
    if (rst)
        result <= 32'd0;
    else
        result <= accumulator + product;
end
endmodule

tb/mac_unit_tb.sv
`timescale 1ns/1ps
module mac_unit_tb;
reg clk,rst;
reg signed [7:0] a,b;
reg signed [31:0] accumulator;
wire signed [31:0] result;

mac_unit uut(.clk(clk), .rst(rst), .a(a), .b(b), .accumulator(accumulator), .result(result));

always #5 clk = ~clk;
initial begin
$dumpfile("sim/mac_unit.vcd");
$dumpvars(0,mac_unit_tb);

clk=0;
rst=1;
a=0;
b=0;
accumulator=0;

#12;
rst=0;

a=8'sd5; b=8'sd3; accumulator=32'sd10;
@(posedge clk);
#1;
$display("Test 1: %d x %d + %d = %d", a, b, accumulator, result);

a=-8'sd5; b=8'sd3; accumulator=32'sd10;
@(posedge clk);
#1;
$display("Test 2: %d x %d + %d = %d", a, b, accumulator, result);

a=8'sd10; b=-8'sd4; accumulator=32'sd50;
@(posedge clk);
#1;
$display("Test 3: %d x %d + %d = %d", a, b, accumulator, result);

$finish;
end
endmodule

sim/mac_unit.vcd
$date
	Sat Sep 12 16:22:11 2026
$end
$version
	Icarus Verilog
$end
$timescale
	1ps
$end
$scope module mac_unit_tb $end
$var wire 32 ! result [31:0] $end
$var reg 8 " a [7:0] $end
$var reg 32 # accumulator [31:0] $end
$var reg 8 $ b [7:0] $end
$var reg 1 % clk $end
$var reg 1 & rst $end
$scope module uut $end
$var wire 8 ' a [7:0] $end
$var wire 32 ( accumulator [31:0] $end
$var wire 8 ) b [7:0] $end
$var wire 1 % clk $end
$var wire 1 & rst $end
$var wire 16 * product [15:0] $end
$var reg 32 + result [31:0] $end
$upscope $end
$upscope $end
$enddefinitions $end
#0
$dumpvars
bx +
b0 *
b0 )
b0 (
b0 '
1&
0%
b0 $
b0 #
b0 "
bx !
$end
#5000
b0 !
b0 +
1%
#10000
0%
#12000
b1010 #
b1010 (
b1111 *
b11 $
b11 )
b101 "
b101 '
0&
#15000
b11001 !
b11001 +
1%
#16000
b1111111111110001 *
b11111011 "
b11111011 '
#20000
0%
#25000
b11111111111111111111111111111011 !
b11111111111111111111111111111011 +
1%
#26000
b110010 #
b110010 (
b11111100 $
b11111100 )
b1111111111011000 *
b1010 "
b1010 '
#30000
0%
#35000
b1010 !
b1010 +
1%
