rtl/output_counter.sv
module output_counter #(
    parameter int total_outputs = 9
)(
    input clk,
    input rst,
    input output_valid,

    output reg processing_done,
    output reg [31:0] output_count
);

    always @(posedge clk) begin

        if (rst) begin

            output_count <= 0;
            processing_done <= 0;

        end

        else if (!processing_done && output_valid) begin

            if (output_count == total_outputs - 1) begin

                output_count <= output_count + 1;
                processing_done <= 1;

            end

            else begin

                output_count <= output_count + 1;
            end

        end

    end

endmodule

tb/output_counter_tb.sv
`timescale 1ns/1ps

module output_counter_tb;
    reg clk;
    reg rst;
    reg output_valid;
    wire processing_done;
    wire [31:0] output_count;
    output_counter #(
        .total_outputs(9)
    ) uut (
        .clk(clk),
        .rst(rst),
        .output_valid(output_valid),
        .processing_done(processing_done),
        .output_count(output_count)
    );
    always #5 clk = ~clk;
    integer i;
    initial begin
        $dumpfile("sim/output_counter.vcd");
        $dumpvars(0, output_counter_tb);
        clk = 0;
        rst = 1;
        output_valid = 0;
        #12;
        rst = 0;
        for (i = 0; i < 9; i = i + 1) begin
            @(negedge clk);
            output_valid = 1;
            @(posedge clk);
            #1;
            $display(
                "Output %0d: count = %0d, done = %0d",
                i + 1,
                output_count,
                processing_done
            );
            @(negedge clk);
            output_valid = 0;
        end
        #10;
        $finish;
    end
endmodule

sim/output_counter.vcd
$date
	Tue Sep 15 22:03:16 2026
$end
$version
	Icarus Verilog
$end
$timescale
	1ps
$end
$scope module output_counter_tb $end
$var wire 1 ! processing_done $end
$var wire 32 " output_count [31:0] $end
$var reg 1 # clk $end
$var reg 1 $ output_valid $end
$var reg 1 % rst $end
$var integer 32 & i [31:0] $end
$scope module uut $end
$var wire 1 # clk $end
$var wire 1 $ output_valid $end
$var wire 1 % rst $end
$var reg 32 ' output_count [31:0] $end
$var reg 1 ! processing_done $end
$upscope $end
$upscope $end
$enddefinitions $end
#0
$dumpvars
bx '
bx &
1%
0$
0#
bx "
x!
$end
#5000
0!
b0 "
b0 '
1#
#10000
0#
#12000
b0 &
0%
#15000
1#
#20000
1$
0#
#25000
b1 "
b1 '
1#
#30000
b1 &
0$
0#
#35000
1#
#40000
1$
0#
#45000
b10 "
b10 '
1#
#50000
b10 &
0$
0#
#55000
1#
#60000
1$
0#
#65000
b11 "
b11 '
1#
#70000
b11 &
0$
0#
#75000
1#
#80000
1$
0#
#85000
b100 "
b100 '
1#
#90000
b100 &
0$
0#
#95000
1#
#100000
1$
0#
#105000
b101 "
b101 '
1#
#110000
b101 &
0$
0#
#115000
1#
#120000
1$
0#
#125000
b110 "
b110 '
1#
#130000
b110 &
0$
0#
#135000
1#
#140000
1$
0#
#145000
b111 "
b111 '
1#
#150000
b111 &
0$
0#
#155000
1#
#160000
1$
0#
#165000
b1000 "
b1000 '
1#
#170000
b1000 &
0$
0#
#175000
1#
#180000
1$
0#
#185000
1!
b1001 "
b1001 '
1#
#190000
b1001 &
0$
0#
#195000
0!
1#
