rtl/sliding_window_3x3.sv
module sliding_window_3x3 #(
    parameter int image_width = 5
)(
    input clk,
    input rst,
    input pixel_valid,

    input signed [7:0] pixel_in,

    output reg window_valid,
    output reg signed [7:0] window [0:8]
);

    reg signed [7:0] line_buffer1 [0:image_width-1];
    reg signed [7:0] line_buffer2 [0:image_width-1];

    reg signed [7:0] row1_left, row1_mid, row1_right;
    reg signed [7:0] row2_left, row2_mid, row2_right;
    reg signed [7:0] row3_left, row3_mid, row3_right;

    integer column;
    integer row_count;
    integer i;

    always @(posedge clk) begin

        if (rst) begin

            column <= 0;
            row_count <= 0;
            window_valid <= 0;

            row1_left <= 0;
            row1_mid <= 0;
            row1_right <= 0;

            row2_left <= 0;
            row2_mid <= 0;
            row2_right <= 0;

            row3_left <= 0;
            row3_mid <= 0;
            row3_right <= 0;

            for (i = 0; i < image_width; i = i + 1) begin
                line_buffer1[i] <= 0;
                line_buffer2[i] <= 0;
            end

            for (i = 0; i < 9; i = i + 1)
                window[i] <= 0;

        end

        else if (pixel_valid) begin

            // Shift row 1
            row1_right <= row1_mid;
            row1_mid   <= row1_left;
            row1_left  <= line_buffer2[column];

            // Shift row 2
            row2_right <= row2_mid;
            row2_mid   <= row2_left;
            row2_left  <= line_buffer1[column];

            // Shift row 3
            row3_right <= row3_mid;
            row3_mid   <= row3_left;
            row3_left  <= pixel_in;

            // Update line buffers
            line_buffer2[column] <= line_buffer1[column];
            line_buffer1[column] <= pixel_in;

            // Generate valid 3x3 window
            if ((row_count >= 2) && (column >= 2)) begin

                window[0] <= row1_mid;
                window[1] <= row1_left;
                window[2] <= line_buffer2[column];

                window[3] <= row2_mid;
                window[4] <= row2_left;
                window[5] <= line_buffer1[column];

                window[6] <= row3_mid;
                window[7] <= row3_left;
                window[8] <= pixel_in;

                window_valid <= 1;

            end
            else begin
                window_valid <= 0;
            end

            // Move column
            if (column == image_width-1) begin

                column <= 0;

                // Move to next row
                if (row_count == image_width-1)
                    row_count <= 0;
                else
                    row_count <= row_count + 1;

            end
            else begin
                column <= column + 1;
            end

        end

        else begin
            window_valid <= 0;
        end

    end

endmodule

tb/sliding_window_3x3_tb.sv
`timescale 1ns/1ps

module sliding_window_3x3_tb;

    localparam int image_width = 5;

    reg clk;
    reg rst;
    reg pixel_valid;
    reg signed [7:0] pixel_in;

    wire signed [7:0] window [0:8];
    wire window_valid;

    sliding_window_3x3 #(
        .image_width(image_width)
    ) uut (
        .clk(clk),
        .rst(rst),
        .pixel_valid(pixel_valid),
        .pixel_in(pixel_in),
        .window(window),
        .window_valid(window_valid)
    );

    // Clock
    always #5 clk = ~clk;

    // Display generated windows
    always @(posedge clk) begin
        #1;

        if (window_valid) begin
            $display(
                "WINDOW: %0d %0d %0d | %0d %0d %0d | %0d %0d %0d",
                window[0], window[1], window[2],
                window[3], window[4], window[5],
                window[6], window[7], window[8]
            );
        end
    end

    initial begin

        $dumpfile("sim/sliding_window_3x3.vcd");
        $dumpvars(0, sliding_window_3x3_tb);

        clk = 0;
        rst = 1;
        pixel_valid = 0;
        pixel_in = 0;

        // Hold reset
        #12;

        // Wait for a falling edge before starting input
        @(negedge clk);

        // Release reset and put first pixel on input
        rst = 0;
        pixel_valid = 1;
        pixel_in = 1;

        // -------------------------
        // Row 1
        // -------------------------

        @(negedge clk); pixel_in = 2;
        @(negedge clk); pixel_in = 3;
        @(negedge clk); pixel_in = 4;
        @(negedge clk); pixel_in = 5;

        // -------------------------
        // Row 2
        // -------------------------

        @(negedge clk); pixel_in = 6;
        @(negedge clk); pixel_in = 7;
        @(negedge clk); pixel_in = 8;
        @(negedge clk); pixel_in = 9;
        @(negedge clk); pixel_in = 10;

        // -------------------------
        // Row 3
        // -------------------------

        @(negedge clk); pixel_in = 11;
        @(negedge clk); pixel_in = 12;
        @(negedge clk); pixel_in = 13;
        @(negedge clk); pixel_in = 14;
        @(negedge clk); pixel_in = 15;

        // -------------------------
        // Row 4
        // -------------------------

        @(negedge clk); pixel_in = 16;
        @(negedge clk); pixel_in = 17;
        @(negedge clk); pixel_in = 18;
        @(negedge clk); pixel_in = 19;
        @(negedge clk); pixel_in = 20;

        // -------------------------
        // Row 5
        // -------------------------

        @(negedge clk); pixel_in = 21;
        @(negedge clk); pixel_in = 22;
        @(negedge clk); pixel_in = 23;
        @(negedge clk); pixel_in = 24;
        @(negedge clk); pixel_in = 25;

        // Allow final output to be observed
        #10;

        $finish;

    end

endmodule

sim/sliding_window_3x3.vcd
$date
	Mon Sep 14 22:35:38 2026
$end
$version
	Icarus Verilog
$end
$timescale
	1ps
$end
$scope module sliding_window_3x3_tb $end
$var wire 1 ! window_valid $end
$var reg 1 " clk $end
$var reg 8 # pixel_in [7:0] $end
$var reg 1 $ pixel_valid $end
$var reg 1 % rst $end
$scope module uut $end
$var wire 1 " clk $end
$var wire 8 & pixel_in [7:0] $end
$var wire 1 $ pixel_valid $end
$var wire 1 % rst $end
$var reg 8 ' row1_left [7:0] $end
$var reg 8 ( row1_mid [7:0] $end
$var reg 8 ) row1_right [7:0] $end
$var reg 8 * row2_left [7:0] $end
$var reg 8 + row2_mid [7:0] $end
$var reg 8 , row2_right [7:0] $end
$var reg 8 - row3_left [7:0] $end
$var reg 8 . row3_mid [7:0] $end
$var reg 8 / row3_right [7:0] $end
$var reg 1 ! window_valid $end
$var integer 32 0 column [31:0] $end
$var integer 32 1 i [31:0] $end
$var integer 32 2 row_count [31:0] $end
$upscope $end
$upscope $end
$enddefinitions $end
#0
$dumpvars
bx 2
bx 1
bx 0
bx /
bx .
bx -
bx ,
bx +
bx *
bx )
bx (
bx '
b0 &
1%
0$
b0 #
0"
x!
$end
#5000
b0 /
b0 .
b0 -
b0 ,
b0 +
b0 *
b0 )
b0 (
b0 '
0!
b0 2
b0 0
b1001 1
1"
#10000
0"
#15000
b1001 1
1"
#20000
b1 #
b1 &
1$
0%
0"
#25000
b1 0
b1 -
1"
#30000
b10 #
b10 &
0"
#35000
b10 0
b10 -
b1 .
1"
#40000
b11 #
b11 &
0"
#45000
b11 0
b11 -
b10 .
b1 /
1"
#50000
b100 #
b100 &
0"
#55000
b100 0
b100 -
b11 .
b10 /
1"
#60000
b101 #
b101 &
0"
#65000
b1 2
b0 0
b101 -
b100 .
b11 /
1"
#70000
b110 #
b110 &
0"
#75000
b1 0
b110 -
b101 .
b100 /
b1 *
1"
#80000
b111 #
b111 &
0"
#85000
b10 0
b111 -
b110 .
b101 /
b10 *
b1 +
1"
#90000
b1000 #
b1000 &
0"
#95000
b11 0
b1000 -
b111 .
b110 /
b11 *
b10 +
b1 ,
1"
#100000
b1001 #
b1001 &
0"
#105000
b100 0
b1001 -
b1000 .
b111 /
b100 *
b11 +
b10 ,
1"
#110000
b1010 #
b1010 &
0"
#115000
b10 2
b0 0
b1010 -
b1001 .
b1000 /
b101 *
b100 +
b11 ,
1"
#120000
b1011 #
b1011 &
0"
#125000
b1 0
b1011 -
b1010 .
b1001 /
b110 *
b101 +
b100 ,
b1 '
1"
#130000
b1100 #
b1100 &
0"
#135000
b10 0
b1100 -
b1011 .
b1010 /
b111 *
b110 +
b101 ,
b10 '
b1 (
1"
#140000
b1101 #
b1101 &
0"
#145000
b11 0
1!
b1101 -
b1100 .
b1011 /
b1000 *
b111 +
b110 ,
b11 '
b10 (
b1 )
1"
#150000
b1110 #
b1110 &
0"
#155000
b100 0
b1110 -
b1101 .
b1100 /
b1001 *
b1000 +
b111 ,
b100 '
b11 (
b10 )
1"
#160000
b1111 #
b1111 &
0"
#165000
b11 2
b0 0
b1111 -
b1110 .
b1101 /
b1010 *
b1001 +
b1000 ,
b101 '
b100 (
b11 )
1"
#170000
b10000 #
b10000 &
0"
#175000
b1 0
0!
b10000 -
b1111 .
b1110 /
b1011 *
b1010 +
b1001 ,
b110 '
b101 (
b100 )
1"
#180000
b10001 #
b10001 &
0"
#185000
b10 0
b10001 -
b10000 .
b1111 /
b1100 *
b1011 +
b1010 ,
b111 '
b110 (
b101 )
1"
#190000
b10010 #
b10010 &
0"
#195000
b11 0
1!
b10010 -
b10001 .
b10000 /
b1101 *
b1100 +
b1011 ,
b1000 '
b111 (
b110 )
1"
#200000
b10011 #
b10011 &
0"
#205000
b100 0
b10011 -
b10010 .
b10001 /
b1110 *
b1101 +
b1100 ,
b1001 '
b1000 (
b111 )
1"
#210000
b10100 #
b10100 &
0"
#215000
b100 2
b0 0
b10100 -
b10011 .
b10010 /
b1111 *
b1110 +
b1101 ,
b1010 '
b1001 (
b1000 )
1"
#220000
b10101 #
b10101 &
0"
#225000
b1 0
0!
b10101 -
b10100 .
b10011 /
b10000 *
b1111 +
b1110 ,
b1011 '
b1010 (
b1001 )
1"
#230000
b10110 #
b10110 &
0"
#235000
b10 0
b10110 -
b10101 .
b10100 /
b10001 *
b10000 +
b1111 ,
b1100 '
b1011 (
b1010 )
1"
#240000
b10111 #
b10111 &
0"
#245000
b11 0
1!
b10111 -
b10110 .
b10101 /
b10010 *
b10001 +
b10000 ,
b1101 '
b1100 (
b1011 )
1"
#250000
b11000 #
b11000 &
0"
#255000
b100 0
b11000 -
b10111 .
b10110 /
b10011 *
b10010 +
b10001 ,
b1110 '
b1101 (
b1100 )
1"
#260000
b11001 #
b11001 &
0"
#265000
b0 2
b0 0
b11001 -
b11000 .
b10111 /
b10100 *
b10011 +
b10010 ,
b1111 '
b1110 (
b1101 )
1"
