rtl/quantizer.sv
module quantizer #(
    parameter int output_width=8,
    parameter int shift=0
)(
    input signed [31:0] data_in,
    output signed [output_width-1:0] data_out
);

wire signed [31:0] shifted_data;

assign shifted_data = data_in >>> shift;
assign data_out = shifted_data[output_width-1:0];

endmodule

rtl/relu.sv
module relu(
    input signed [31:0] data_in,
    output signed [31:0] data_out
);
assign data_out = (data_in>0) ? data_in : 32'sd0;
endmodule

rtl/mac_array.sv
module mac_array #(
    parameter int num_mac = 9
)(
    input signed [7:0] a [0:num_mac-1],
    input signed [7:0] b [0:num_mac-1],
    output reg signed [31:0] result
);
reg signed [15:0] product [0:num_mac-1];
integer i;
always @ (*) begin
   for (i=0;i<num_mac;i=i+1) begin
    product[i]=a[i]*b[i];
   end
   result=32'd0;
   for (i=0;i<num_mac;i=i+1) begin
    result=result+product[i];
   end
end
endmodule

rtl/convolution_3x3.sv
module convolution_3x3(
    input signed [7:0] pixels [0:8],
    input signed [7:0] weights [0:8],
    output signed [31:0] result
);
mac_array #(
    .num_mac(9)
) mac_engine (
    .a(pixels),
    .b(weights),
    .result(result)
);
endmodule

rtl/sliding_window_3x3.sv
module sliding_window_3x3 #(
    parameter int image_width = 5
)(
    input clk,
    input rst,
    input pixel_valid,

    input signed [7:0] pixel_in,

    output reg window_valid,
    output reg signed [7:0] window [0:8]
);

    reg signed [7:0] line_buffer1 [0:image_width-1];
    reg signed [7:0] line_buffer2 [0:image_width-1];

    reg signed [7:0] row1_left, row1_mid, row1_right;
    reg signed [7:0] row2_left, row2_mid, row2_right;
    reg signed [7:0] row3_left, row3_mid, row3_right;

    integer column;
    integer row_count;
    integer i;

    always @(posedge clk) begin

        if (rst) begin

            column <= 0;
            row_count <= 0;
            window_valid <= 0;

            row1_left <= 0;
            row1_mid <= 0;
            row1_right <= 0;

            row2_left <= 0;
            row2_mid <= 0;
            row2_right <= 0;

            row3_left <= 0;
            row3_mid <= 0;
            row3_right <= 0;

            for (i = 0; i < image_width; i = i + 1) begin
                line_buffer1[i] <= 0;
                line_buffer2[i] <= 0;
            end

            for (i = 0; i < 9; i = i + 1)
                window[i] <= 0;

        end

        else if (pixel_valid) begin

            // Shift row 1
            row1_right <= row1_mid;
            row1_mid   <= row1_left;
            row1_left  <= line_buffer2[column];

            // Shift row 2
            row2_right <= row2_mid;
            row2_mid   <= row2_left;
            row2_left  <= line_buffer1[column];

            // Shift row 3
            row3_right <= row3_mid;
            row3_mid   <= row3_left;
            row3_left  <= pixel_in;

            // Update line buffers
            line_buffer2[column] <= line_buffer1[column];
            line_buffer1[column] <= pixel_in;

            // Generate valid 3x3 window
            if ((row_count >= 2) && (column >= 2)) begin

                window[0] <= row1_mid;
                window[1] <= row1_left;
                window[2] <= line_buffer2[column];

                window[3] <= row2_mid;
                window[4] <= row2_left;
                window[5] <= line_buffer1[column];

                window[6] <= row3_mid;
                window[7] <= row3_left;
                window[8] <= pixel_in;

                window_valid <= 1;

            end
            else begin
                window_valid <= 0;
            end

            // Move column
            if (column == image_width-1) begin

                column <= 0;

                // Move to next row
                if (row_count == image_width-1)
                    row_count <= 0;
                else
                    row_count <= row_count + 1;

            end
            else begin
                column <= column + 1;
            end

        end

        else begin
            window_valid <= 0;
        end

    end

endmodule

rtl/streaming_convolution.sv
module streaming_convolution #(
    parameter int image_width = 5
)(
    input clk, rst, pixel_valid,
    input signed [7:0] pixel_in,
    input signed [7:0] weights [0:8],
    output wire output_valid,
    output wire signed [7:0] quantized_out
);
wire signed [7:0] window [0:8];
wire window_valid;
sliding_window_3x3 #(
    .image_width(image_width)
) window_generator (
    .clk(clk),
    .rst(rst),
    .pixel_valid(pixel_valid),
    .pixel_in(pixel_in),
    .window(window),
    .window_valid(window_valid)
);

wire signed [31:0] raw_conv_result;

convolution_3x3 uut(
    .weights(weights),
    .result(raw_conv_result),
    .pixels(window)
);

wire signed [31:0] relu_result;

relu dut(
    .data_in(raw_conv_result),
    .data_out(relu_result)
);

quantizer #(
    .output_width(8),
    .shift(2)
) fut(
    .data_in(relu_result),
    .data_out(quantized_out)
);

assign output_valid=window_valid;
endmodule

tb/streaming_convolution_tb.sv
`timescale 1ns/1ps

module streaming_convolution_tb;

localparam int image_width = 5;
reg clk, rst, pixel_valid;
reg signed [7:0] pixel_in;
reg signed [7:0] weights [0:8];
wire output_valid;
wire signed [7:0] quantized_out;

streaming_convolution  #(
    .image_width(image_width)
) uut(
    .clk(clk), .rst(rst), .pixel_valid(pixel_valid),
    .pixel_in(pixel_in), .weights(weights),
    .output_valid(output_valid), .quantized_out(quantized_out)
);

always #5 clk=~clk;

always @(posedge clk) begin
    #1;
    if(output_valid) begin
        $display("Result: %d", quantized_out);
    end
end

initial begin
    $dumpfile("sim/streaming_convolution.vcd");
    $dumpvars(0,streaming_convolution_tb);

    clk=0;
    rst=1;
    pixel_in=0;
    pixel_valid=0;

    weights[0] = 1;
    weights[1] = 1;
    weights[2] = 1;
    weights[3] = 1;
    weights[4] = 1;
    weights[5] = 1;
    weights[6] = 1;
    weights[7] = 1;
    weights[8] = 1;

    #12;
    @(negedge clk) 
    rst=0; pixel_valid=1; pixel_in=1;
    @(negedge clk) pixel_in = 2;
    @(negedge clk) pixel_in = 3;
    @(negedge clk) pixel_in = 4;
    @(negedge clk) pixel_in = 5;
    @(negedge clk) pixel_in = 6;
    @(negedge clk) pixel_in = 7;
    @(negedge clk) pixel_in = 8;
    @(negedge clk) pixel_in = 9;
    @(negedge clk) pixel_in = 10;
    @(negedge clk) pixel_in = 11;
    @(negedge clk) pixel_in = 12;
    @(negedge clk) pixel_in = 13;
    @(negedge clk) pixel_in = 14;
    @(negedge clk) pixel_in = 15;
    @(negedge clk) pixel_in = 16;
    @(negedge clk) pixel_in = 17;
    @(negedge clk) pixel_in = 18;
    @(negedge clk) pixel_in = 19;
    @(negedge clk) pixel_in = 20;
    @(negedge clk) pixel_in = 21;
    @(negedge clk) pixel_in = 22;
    @(negedge clk) pixel_in = 23;
    @(negedge clk) pixel_in = 24;
    @(negedge clk) pixel_in = 25;
    #10;
    $finish;
end
endmodule

sim/streaming_convolution.vcd
$date
	Tue Sep 15 16:00:34 2026
$end
$version
	Icarus Verilog
$end
$timescale
	1ps
$end
$scope module streaming_convolution_tb $end
$var wire 8 ! quantized_out [7:0] $end
$var wire 1 " output_valid $end
$var reg 1 # clk $end
$var reg 8 $ pixel_in [7:0] $end
$var reg 1 % pixel_valid $end
$var reg 1 & rst $end
$scope module uut $end
$var wire 1 # clk $end
$var wire 1 " output_valid $end
$var wire 8 ' pixel_in [7:0] $end
$var wire 1 % pixel_valid $end
$var wire 1 & rst $end
$var wire 1 ( window_valid $end
$var wire 32 ) relu_result [31:0] $end
$var wire 32 * raw_conv_result [31:0] $end
$var wire 8 + quantized_out [7:0] $end
$scope module dut $end
$var wire 32 , data_out [31:0] $end
$var wire 32 - data_in [31:0] $end
$upscope $end
$scope module fut $end
$var wire 32 . data_in [31:0] $end
$var wire 32 / shifted_data [31:0] $end
$var wire 8 0 data_out [7:0] $end
$upscope $end
$scope module uut $end
$var wire 32 1 result [31:0] $end
$scope module mac_engine $end
$var reg 32 2 result [31:0] $end
$var integer 32 3 i [31:0] $end
$upscope $end
$upscope $end
$scope module window_generator $end
$var wire 1 # clk $end
$var wire 8 4 pixel_in [7:0] $end
$var wire 1 % pixel_valid $end
$var wire 1 & rst $end
$var reg 8 5 row1_left [7:0] $end
$var reg 8 6 row1_mid [7:0] $end
$var reg 8 7 row1_right [7:0] $end
$var reg 8 8 row2_left [7:0] $end
$var reg 8 9 row2_mid [7:0] $end
$var reg 8 : row2_right [7:0] $end
$var reg 8 ; row3_left [7:0] $end
$var reg 8 < row3_mid [7:0] $end
$var reg 8 = row3_right [7:0] $end
$var reg 1 ( window_valid $end
$var integer 32 > column [31:0] $end
$var integer 32 ? i [31:0] $end
$var integer 32 @ row_count [31:0] $end
$upscope $end
$upscope $end
$upscope $end
$enddefinitions $end
#0
$dumpvars
bx @
bx ?
bx >
bx =
bx <
bx ;
bx :
bx 9
bx 8
bx 7
bx 6
bx 5
b0 4
b1001 3
bx 2
bx 1
bx 0
bx /
bx .
bx -
bx ,
bx +
bx *
bx )
x(
b0 '
1&
0%
b0 $
0#
x"
bx !
$end
#5000
b0 !
b0 +
b0 0
b0 /
b0 )
b0 ,
b0 .
b0 *
b0 -
b0 1
b0 2
b1001 3
b0 =
b0 <
b0 ;
b0 :
b0 9
b0 8
b0 7
b0 6
b0 5
0"
0(
b0 @
b0 >
b1001 ?
1#
#10000
0#
#15000
b1001 ?
1#
#20000
b1 $
b1 '
b1 4
1%
0&
0#
#25000
b1 >
b1 ;
1#
#30000
b10 $
b10 '
b10 4
0#
#35000
b10 >
b10 ;
b1 <
1#
#40000
b11 $
b11 '
b11 4
0#
#45000
b11 >
b11 ;
b10 <
b1 =
1#
#50000
b100 $
b100 '
b100 4
0#
#55000
b100 >
b100 ;
b11 <
b10 =
1#
#60000
b101 $
b101 '
b101 4
0#
#65000
b1 @
b0 >
b101 ;
b100 <
b11 =
1#
#70000
b110 $
b110 '
b110 4
0#
#75000
b1 >
b110 ;
b101 <
b100 =
b1 8
1#
#80000
b111 $
b111 '
b111 4
0#
#85000
b10 >
b111 ;
b110 <
b101 =
b10 8
b1 9
1#
#90000
b1000 $
b1000 '
b1000 4
0#
#95000
b11 >
b1000 ;
b111 <
b110 =
b11 8
b10 9
b1 :
1#
#100000
b1001 $
b1001 '
b1001 4
0#
#105000
b100 >
b1001 ;
b1000 <
b111 =
b100 8
b11 9
b10 :
1#
#110000
b1010 $
b1010 '
b1010 4
0#
#115000
b10 @
b0 >
b1010 ;
b1001 <
b1000 =
b101 8
b100 9
b11 :
1#
#120000
b1011 $
b1011 '
b1011 4
0#
#125000
b1 >
b1011 ;
b1010 <
b1001 =
b110 8
b101 9
b100 :
b1 5
1#
#130000
b1100 $
b1100 '
b1100 4
0#
#135000
b10 >
b1100 ;
b1011 <
b1010 =
b111 8
b110 9
b101 :
b10 5
b1 6
1#
#140000
b1101 $
b1101 '
b1101 4
0#
#145000
b1111 !
b1111 +
b1111 0
b1111 /
b111111 )
b111111 ,
b111111 .
b111111 *
b111111 -
b111111 1
b111111 2
b1001 3
b11 >
1"
1(
b1101 ;
b1100 <
b1011 =
b1000 8
b111 9
b110 :
b11 5
b10 6
b1 7
1#
#150000
b1110 $
b1110 '
b1110 4
0#
#155000
b10010 !
b10010 +
b10010 0
b10010 /
b1001000 )
b1001000 ,
b1001000 .
b1001000 *
b1001000 -
b1001000 1
b1001000 2
b1001 3
b100 >
b1110 ;
b1101 <
b1100 =
b1001 8
b1000 9
b111 :
b100 5
b11 6
b10 7
1#
#160000
b1111 $
b1111 '
b1111 4
0#
#165000
b10100 !
b10100 +
b10100 0
b10100 /
b1010001 )
b1010001 ,
b1010001 .
b1010001 *
b1010001 -
b1010001 1
b1010001 2
b1001 3
b11 @
b0 >
b1111 ;
b1110 <
b1101 =
b1010 8
b1001 9
b1000 :
b101 5
b100 6
b11 7
1#
#170000
b10000 $
b10000 '
b10000 4
0#
#175000
b1 >
0"
0(
b10000 ;
b1111 <
b1110 =
b1011 8
b1010 9
b1001 :
b110 5
b101 6
b100 7
1#
#180000
b10001 $
b10001 '
b10001 4
0#
#185000
b10 >
b10001 ;
b10000 <
b1111 =
b1100 8
b1011 9
b1010 :
b111 5
b110 6
b101 7
1#
#190000
b10010 $
b10010 '
b10010 4
0#
#195000
b11011 !
b11011 +
b11011 0
b11011 /
b1101100 )
b1101100 ,
b1101100 .
b1101100 *
b1101100 -
b1101100 1
b1101100 2
b1001 3
b11 >
1"
1(
b10010 ;
b10001 <
b10000 =
b1101 8
b1100 9
b1011 :
b1000 5
b111 6
b110 7
1#
#200000
b10011 $
b10011 '
b10011 4
0#
#205000
b11101 !
b11101 +
b11101 0
b11101 /
b1110101 )
b1110101 ,
b1110101 .
b1110101 *
b1110101 -
b1110101 1
b1110101 2
b1001 3
b100 >
b10011 ;
b10010 <
b10001 =
b1110 8
b1101 9
b1100 :
b1001 5
b1000 6
b111 7
1#
#210000
b10100 $
b10100 '
b10100 4
0#
#215000
b11111 !
b11111 +
b11111 0
b11111 /
b1111110 )
b1111110 ,
b1111110 .
b1111110 *
b1111110 -
b1111110 1
b1111110 2
b1001 3
b100 @
b0 >
b10100 ;
b10011 <
b10010 =
b1111 8
b1110 9
b1101 :
b1010 5
b1001 6
b1000 7
1#
#220000
b10101 $
b10101 '
b10101 4
0#
#225000
b1 >
0"
0(
b10101 ;
b10100 <
b10011 =
b10000 8
b1111 9
b1110 :
b1011 5
b1010 6
b1001 7
1#
#230000
b10110 $
b10110 '
b10110 4
0#
#235000
b10 >
b10110 ;
b10101 <
b10100 =
b10001 8
b10000 9
b1111 :
b1100 5
b1011 6
b1010 7
1#
#240000
b10111 $
b10111 '
b10111 4
0#
#245000
b100110 !
b100110 +
b100110 0
b100110 /
b10011001 )
b10011001 ,
b10011001 .
b10011001 *
b10011001 -
b10011001 1
b10011001 2
b1001 3
b11 >
1"
1(
b10111 ;
b10110 <
b10101 =
b10010 8
b10001 9
b10000 :
b1101 5
b1100 6
b1011 7
1#
#250000
b11000 $
b11000 '
b11000 4
0#
#255000
b101000 !
b101000 +
b101000 0
b101000 /
b10100010 )
b10100010 ,
b10100010 .
b10100010 *
b10100010 -
b10100010 1
b10100010 2
b1001 3
b100 >
b11000 ;
b10111 <
b10110 =
b10011 8
b10010 9
b10001 :
b1110 5
b1101 6
b1100 7
1#
#260000
b11001 $
b11001 '
b11001 4
0#
#265000
b101010 !
b101010 +
b101010 0
b101010 /
b10101011 )
b10101011 ,
b10101011 .
b10101011 *
b10101011 -
b10101011 1
b10101011 2
b1001 3
b0 @
b0 >
b11001 ;
b11000 <
b10111 =
b10100 8
b10011 9
b10010 :
b1111 5
b1110 6
b1101 7
1#
